as_you_wish/__init__.py
as_you_wish/as_you_wish.py
as_you_wish-0.1.0.dist-info/LICENSE
as_you_wish-0.1.0.dist-info/METADATA
as_you_wish-0.1.0.dist-info/WHEEL
as_you_wish-0.1.0.dist-info/RECORD
