Metadata-Version: 2.1
Name: as-you-wish
Version: 0.1.0
Summary: A simple python configuration lib.
Home-page: https://github.com/lochnessdragon/as-you-wish
License: MIT
Keywords: config,ini
Author: Lochnessdragon
Author-email: 39635811+lochnessdragon@users.noreply.github.com
Requires-Python: >=3.7.0,<4.0.0
Classifier: Environment :: Web Environment
Classifier: Intended Audience :: Developers
Classifier: License :: OSI Approved :: MIT License
Classifier: Operating System :: OS Independent
Classifier: Programming Language :: Python :: 3
Classifier: Programming Language :: Python :: 3.7
Classifier: Programming Language :: Python :: 3.8
Classifier: Programming Language :: Python :: 3.9
Classifier: Programming Language :: Python :: 3.10
Classifier: Programming Language :: Python :: 3.11
Classifier: Programming Language :: Python :: 3
Provides-Extra: docs
Requires-Dist: Sphinx (==5.0.0) ; extra == "docs"
Requires-Dist: furo (==2022.12.7) ; extra == "docs"
Project-URL: Repository, https://github.com/lochnessdragon/as-you-wish
